{
  "name": "AKAS Document Ingestion and Query Workflow",
  "nodes": [
    {
      "parameters": {
        "httpMethod": "POST",
        "url": "http://backend:8000/ingest/",
        "options": {},
        "responseFormat": "json",
        "bodyParametersUi": {
          "parameter": [
            {
              "name": "file",
              "value": "={{$json[\"file\"]}}"
            }
          ]
        }
      },
      "name": "Ingest Document",
      "type": "n8n-nodes-base.httpRequest",
      "typeVersion": 1,
      "position": [450, 300]
    },
    {
      "parameters": {
        "httpMethod": "POST",
        "url": "http://backend:8000/query/",
        "options": {},
        "responseFormat": "json",
        "queryParametersUi": {
          "parameter": [
            {
              "name": "q",
              "value": "={{$json[\"question\"]}}"
            }
          ]
        }
      },
      "name": "Query",
      "type": "n8n-nodes-base.httpRequest",
      "typeVersion": 1,
      "position": [650, 300]
    }
  ],
  "connections": {
    "Ingest Document": {
      "main": [
        [
          {
            "node": "Query",
            "type": "main",
            "index": 0
          }
        ]
      ]
    }
  }
}
